odoo/addons/account_invoice_consolidated/README.rst
odoo/addons/account_invoice_consolidated/__init__.py
odoo/addons/account_invoice_consolidated/__manifest__.py
odoo/addons/account_invoice_consolidated/data/account_invoice_consolidated_data.xml
odoo/addons/account_invoice_consolidated/i18n/account_invoice_consolidated.pot
odoo/addons/account_invoice_consolidated/i18n/pt.po
odoo/addons/account_invoice_consolidated/migrations/14.0.1.0.1/post-migrate.py
odoo/addons/account_invoice_consolidated/models/__init__.py
odoo/addons/account_invoice_consolidated/models/account_invoice_consolidated.py
odoo/addons/account_invoice_consolidated/models/account_move.py
odoo/addons/account_invoice_consolidated/models/account_move_line.py
odoo/addons/account_invoice_consolidated/models/account_payment.py
odoo/addons/account_invoice_consolidated/models/res_company.py
odoo/addons/account_invoice_consolidated/models/res_partner.py
odoo/addons/account_invoice_consolidated/readme/CONFIGURE.rst
odoo/addons/account_invoice_consolidated/readme/CONTRIBUTORS.rst
odoo/addons/account_invoice_consolidated/readme/CREDITS.rst
odoo/addons/account_invoice_consolidated/readme/DESCRIPTION.rst
odoo/addons/account_invoice_consolidated/readme/USAGE.rst
odoo/addons/account_invoice_consolidated/security/account_invoice_consolidated_security.xml
odoo/addons/account_invoice_consolidated/security/ir.model.access.csv
odoo/addons/account_invoice_consolidated/static/description/icon.png
odoo/addons/account_invoice_consolidated/static/description/index.html
odoo/addons/account_invoice_consolidated/tests/__init__.py
odoo/addons/account_invoice_consolidated/tests/test_consolidated_invoices.py
odoo/addons/account_invoice_consolidated/tests/test_consolidated_invoices_data.xml
odoo/addons/account_invoice_consolidated/views/account_invoice_consolidated_view.xml
odoo/addons/account_invoice_consolidated/views/account_move_view.xml
odoo/addons/account_invoice_consolidated/views/account_payment_view.xml
odoo14_addon_account_invoice_consolidated-14.0.1.0.4.dist-info/METADATA
odoo14_addon_account_invoice_consolidated-14.0.1.0.4.dist-info/WHEEL
odoo14_addon_account_invoice_consolidated-14.0.1.0.4.dist-info/top_level.txt
odoo14_addon_account_invoice_consolidated-14.0.1.0.4.dist-info/RECORD
